swarmauri_vectorstore_neo4j/Neo4jVectorStore.py
swarmauri_vectorstore_neo4j/__init__.py
swarmauri_vectorstore_neo4j-0.7.5.dist-info/LICENSE
swarmauri_vectorstore_neo4j-0.7.5.dist-info/METADATA
swarmauri_vectorstore_neo4j-0.7.5.dist-info/WHEEL
swarmauri_vectorstore_neo4j-0.7.5.dist-info/entry_points.txt
swarmauri_vectorstore_neo4j-0.7.5.dist-info/RECORD
